pyudk/__init__.py
pyudk/mechanics.py
pyudk-1.0.6.dist-info/LICENSE
pyudk-1.0.6.dist-info/METADATA
pyudk-1.0.6.dist-info/WHEEL
pyudk-1.0.6.dist-info/top_level.txt
pyudk-1.0.6.dist-info/RECORD
