Metadata-Version: 2.1
Name: pyudk
Version: 1.0.6
Summary: Computes Udwadia–Kalaba constraint forces of an equation of motion of a constrained mechanical system.
Home-page: https://github.com/Eddy-Morgan/PyUdK
Author: Edward Morgan
Author-email: emorg31@lsu.edu
License: MIT
Keywords: python,pyUdK,Udwadia Kalaba,constraint,gaussian,equation of motion,constrained mechanical system
Classifier: Development Status :: 2 - Pre-Alpha
Classifier: Intended Audience :: Science/Research
Classifier: Programming Language :: Python :: 3
Classifier: Operating System :: Unix
Classifier: Operating System :: MacOS :: MacOS X
Classifier: Operating System :: Microsoft :: Windows
Classifier: License :: OSI Approved :: MIT License
Classifier: Topic :: Scientific/Engineering
License-File: LICENSE
Requires-Dist: atomicwrites (==1.4.1)
Requires-Dist: attrs (==22.2.0)
Requires-Dist: more-itertools (==9.0.0)
Requires-Dist: mpmath (==1.2.1)
Requires-Dist: numpy (==1.24.1)
Requires-Dist: pluggy (==1.0.0)
Requires-Dist: py (==1.11.0)
Requires-Dist: pytest (==4.4.1)
Requires-Dist: pytest-runner (==4.4)
Requires-Dist: scipy (==1.10.0)
Requires-Dist: six (==1.16.0)
Requires-Dist: sympy (==1.11.1)
